LICENSE
MANIFEST.in
README.md
package.json
setup.py
dash_video_component/DashVideoComponent.py
dash_video_component/__init__.py
dash_video_component/_imports_.py
dash_video_component/dash_video_component.min.js
dash_video_component/dash_video_component.min.js.map
dash_video_component/metadata.json
dash_video_component/package-info.json
dash_video_component/video-react.css
dash_video_component.egg-info/PKG-INFO
dash_video_component.egg-info/SOURCES.txt
dash_video_component.egg-info/dependency_links.txt
dash_video_component.egg-info/top_level.txt