Metadata-Version: 1.1
Name: dash-video-component
Version: 0.0.1
Summary: Video Component for Dash
Home-page: UNKNOWN
Author: Matthias Lochbrunner <matthias_lochbrunner@web.de>
Author-email: UNKNOWN
License: MIT
Platform: UNKNOWN
Classifier: Framework :: Dash
